tnh_scholar/__init__.py
tnh_scholar/ai_text_processing/__init__.py
tnh_scholar/ai_text_processing/ai_text_processing.py
tnh_scholar/ai_text_processing/general_processor.py
tnh_scholar/ai_text_processing/line_translator.py
tnh_scholar/ai_text_processing/openai_process_interface.py
tnh_scholar/ai_text_processing/prompts.py
tnh_scholar/ai_text_processing/response_format.py
tnh_scholar/ai_text_processing/section_processor.py
tnh_scholar/ai_text_processing/text_object.py
tnh_scholar/ai_text_processing/typing.py
tnh_scholar/audio_processing/__init__.py
tnh_scholar/audio_processing/audio_legacy.py
tnh_scholar/audio_processing/diarization/__init__.py
tnh_scholar/audio_processing/diarization/_diarization_utils.py
tnh_scholar/audio_processing/diarization/audio/__init__.py
tnh_scholar/audio_processing/diarization/audio/config.py
tnh_scholar/audio_processing/diarization/audio/handler.py
tnh_scholar/audio_processing/diarization/chunker.py
tnh_scholar/audio_processing/diarization/config.py
tnh_scholar/audio_processing/diarization/models.py
tnh_scholar/audio_processing/diarization/protocols.py
tnh_scholar/audio_processing/diarization/pyannote_adapter.py
tnh_scholar/audio_processing/diarization/pyannote_client.py
tnh_scholar/audio_processing/diarization/pyannote_diarize.py
tnh_scholar/audio_processing/diarization/reaper/reaper_roundtrip_poc.py
tnh_scholar/audio_processing/diarization/schemas.py
tnh_scholar/audio_processing/diarization/strategies/__init__.py
tnh_scholar/audio_processing/diarization/strategies/language_based.py
tnh_scholar/audio_processing/diarization/strategies/language_probe.py
tnh_scholar/audio_processing/diarization/strategies/speaker_blocker.py
tnh_scholar/audio_processing/diarization/strategies/time_gap.py
tnh_scholar/audio_processing/diarization/timeline_mapper.py
tnh_scholar/audio_processing/diarization/types.py
tnh_scholar/audio_processing/diarization/viewer.py
tnh_scholar/audio_processing/timed_object/__init__.py
tnh_scholar-0.3.0.dist-info/METADATA
tnh_scholar-0.3.0.dist-info/WHEEL
tnh_scholar-0.3.0.dist-info/entry_points.txt
tnh_scholar-0.3.0.dist-info/licenses/LICENSE
tnh_scholar-0.3.0.dist-info/RECORD
