Metadata-Version: 2.4
Name: tnh-scholar
Version: 0.3.0
Summary: TNH Scholar is an AI-driven project designed to explore, query, and translate the teachings of Thich Nhat Hanh and Plum Village community.
License: GPL-3.0-only
License-File: LICENSE
Keywords: nlp,dharma,processing,text,translation,ai
Author: Aaron K. Solomon
Author-email: aaron.kyle.solomon@gmail.com
Requires-Python: >=3.12,<3.13
Classifier: Development Status :: 3 - Alpha
Classifier: Intended Audience :: Science/Research
Classifier: License :: OSI Approved :: GNU General Public License v3 (GPLv3)
Classifier: Programming Language :: Python :: 3
Classifier: Programming Language :: Python :: 3.12
Provides-Extra: gui
Provides-Extra: ocr
Provides-Extra: query
Requires-Dist: assemblyai (==0.34.0)
Requires-Dist: beautifulsoup4 (==4.12.3) ; extra == "query"
Requires-Dist: click (==8.1.8)
Requires-Dist: colorlog (==6.9.0)
Requires-Dist: ebooklib (==0.18) ; extra == "query"
Requires-Dist: fitz (==0.0.1.dev2) ; extra == "ocr"
Requires-Dist: flask (==3.1.0)
Requires-Dist: gitpython (==3.1.44)
Requires-Dist: google-cloud (==0.34.0) ; extra == "ocr"
Requires-Dist: google-cloud-vision (==3.9.0) ; extra == "ocr"
Requires-Dist: jinja2 (==3.1.5)
Requires-Dist: langchain-community (==0.3.13) ; extra == "gui"
Requires-Dist: langdetect (==1.0.9)
Requires-Dist: lxml (==5.3.0)
Requires-Dist: nltk (==3.9.1)
Requires-Dist: numpy (==2.0.2)
Requires-Dist: openai (==2.5.0)
Requires-Dist: openai-whisper (==20240930)
Requires-Dist: packaging (==24.2)
Requires-Dist: pdf2image (==1.17.0) ; extra == "ocr"
Requires-Dist: pillow (==11.1.0) ; extra == "ocr"
Requires-Dist: platformdirs (==4.3.6)
Requires-Dist: pycountry (==24.6.1)
Requires-Dist: pydantic (==2.10.4)
Requires-Dist: pydantic-settings (==2.6.1)
Requires-Dist: pydub (==0.25.1)
Requires-Dist: pyngrok (==7.2.3)
Requires-Dist: pysrt (==1.1.2)
Requires-Dist: python-dotenv (==1.0.1)
Requires-Dist: python-json-logger (==2.0.7)
Requires-Dist: pyyaml (==6.0.2)
Requires-Dist: regex (==2024.11.6)
Requires-Dist: requests (==2.32.3)
Requires-Dist: spacy (==3.8.3) ; extra == "query"
Requires-Dist: streamlit (==1.41.1) ; extra == "gui"
Requires-Dist: supabase (==2.11.0) ; extra == "gui"
Requires-Dist: tenacity (==9.0.0)
Requires-Dist: tiktoken (==0.8.0)
Requires-Dist: torch (==2.5.1)
Requires-Dist: tqdm (==4.67.1)
Requires-Dist: transformers (==4.48)
Requires-Dist: typer (==0.12.5)
Requires-Dist: unidecode (==1.3.8)
Requires-Dist: yt-dlp (>=2025.1.15)
Project-URL: Bug Tracker, https://github.com/aaronksolomon/tnh-scholar/issues
Project-URL: Documentation, https://aaronksolomon.github.io/tnh-scholar/
Project-URL: Homepage, https://aaronksolomon.github.io/tnh-scholar/
